leetcode_daily/__init__.py
leetcode_daily/leetcode.py
leetcode_daily/main.py
leetcode_daily-1.0.0.dist-info/METADATA
leetcode_daily-1.0.0.dist-info/WHEEL
leetcode_daily-1.0.0.dist-info/entry_points.txt
leetcode_daily-1.0.0.dist-info/top_level.txt
leetcode_daily-1.0.0.dist-info/RECORD
