Metadata-Version: 2.4
Name: leetcode_daily
Version: 1.0.0
Author: happydave1
Requires-Dist: certifi==2025.4.26
Requires-Dist: charset-normalizer==3.4.2
Requires-Dist: idna==3.10
Requires-Dist: requests==2.32.3
Requires-Dist: setuptools==80.9.0
Requires-Dist: urllib3==2.4.0
Dynamic: author
Dynamic: requires-dist
